pupil_tracking/__init__.py
pupil_tracking-1.0.1.dist-info/LICENSE
pupil_tracking-1.0.1.dist-info/METADATA
pupil_tracking-1.0.1.dist-info/WHEEL
pupil_tracking-1.0.1.dist-info/top_level.txt
pupil_tracking-1.0.1.dist-info/RECORD
