Metadata-Version: 2.1
Name: pupil-tracking
Version: 1.0.1
Summary: This is package for using ML to learn pupil tracking, under the direction of Professor Iman Soltani UC Davis MAE Department.
Home-page: https://github.com/JonnyD1117/Pupil_Tracking
Author: Jonathan T. Dorsey
Author-email: jtdorsey@ucdavis.edu
License: MIT
Platform: UNKNOWN
Requires-Python: >=3.8
